LICENSE
README.rst
pyproject.toml
setup.py
cravat/__init__.py
cravat/__main__.py
cravat/constants.py
cravat/cravat_report.py
cravat/exceptions.py
cravat/inout.py
cravat/util.py
cravat/api/__init__.py
cravat/api/config.py
cravat/api/new.py
cravat/api/system.py
cravat/api/test.py
cravat/api/util.py
cravat/api/module/__init__.py
cravat/api/module/install_defs.py
cravat/api/module/ls_logic.py
cravat/api/store/__init__.py
cravat/api/store/account/__init__.py
cravat/cli/__init__.py
cravat/cli/config.py
cravat/cli/gui.py
cravat/cli/issue.py
cravat/cli/license.py
cravat/cli/new.py
cravat/cli/report.py
cravat/cli/run.py
cravat/cli/system.py
cravat/cli/test.py
cravat/cli/update.py
cravat/cli/util.py
cravat/cli/version.py
cravat/cli/module/__init__.py
cravat/cli/module/info_fn.py
cravat/cli/module/install_defs.py
cravat/cli/module/ls.py
cravat/cli/store/__init__.py
cravat/cli/store/account/__init__.py
cravat/gui/consts.py
cravat/gui/job_handlers.py
cravat/gui/multiuser.py
cravat/gui/server.py
cravat/gui/serveradmindb.py
cravat/gui/store_handlers.py
cravat/gui/system_handlers.py
cravat/gui/system_message_db.py
cravat/gui/system_worker.py
cravat/gui/userjob.py
cravat/gui/util.py
cravat/gui/web_submit.py
cravat/gui/websocket_handlers.py
cravat/gui/webresult/__init__.py
cravat/gui/webresult/jsonreporter.py
cravat/gui/webresult/webresult.py
cravat/lib/__init__.py
cravat/lib/consts.py
cravat/lib/exceptions.py
cravat/lib/assets/module_templates/annotator/template.py
cravat/lib/assets/module_templates/converter/template.py
cravat/lib/assets/module_templates/mapper/template.py
cravat/lib/assets/module_templates/postaggregator/template.py
cravat/lib/assets/module_templates/preparer/template.py
cravat/lib/assets/module_templates/reporter/template.py
cravat/lib/base/__init__.py
cravat/lib/base/aggregator.py
cravat/lib/base/annotator.py
cravat/lib/base/app.py
cravat/lib/base/commonmodule.py
cravat/lib/base/converter.py
cravat/lib/base/mapper.py
cravat/lib/base/master_converter.py
oakvar.egg-info/PKG-INFO
oakvar.egg-info/SOURCES.txt
oakvar.egg-info/dependency_links.txt
oakvar.egg-info/entry_points.txt
oakvar.egg-info/requires.txt
oakvar.egg-info/top_level.txt
