Metadata-Version: 2.4
Name: oakvar
Version: 2.12.24
Summary: A genomic variant analysis platform
Home-page: https://github.com/rkimoakbioinformatics/oakvar
Author: Ryangguk Kim
Author-email: rkim@oakbioinformatics.com
Project-URL: Documentation, https://oakvar.readthedocs.io
Project-URL: Source, https://github.com/rkimoakbioinformatics/oakvar
Project-URL: Tracker, https://github.com/rkimoakbioinformatics/oakvar/issues
Keywords: genomic variant analysis interpretation genome
Classifier: 
Requires-Python: >=3.8
License-File: LICENSE
Requires-Dist: requests
Requires-Dist: requests-toolbelt
Requires-Dist: liftover
Requires-Dist: markdown
Requires-Dist: aiohttp<4.0.0
Requires-Dist: chardet>=3.0.4
Requires-Dist: aiosqlite
Requires-Dist: oyaml
Requires-Dist: nest-asyncio
Requires-Dist: psutil
Requires-Dist: python-dateutil
Requires-Dist: download
Requires-Dist: gdown
Requires-Dist: split-file-reader
Requires-Dist: packaging
Requires-Dist: Pillow
Requires-Dist: duckdb
Requires-Dist: rich
Requires-Dist: aiohttp-cors
Requires-Dist: pyjwt
Requires-Dist: polars>=1.9.0
Requires-Dist: connectorx
Requires-Dist: pyarrow
Requires-Dist: multiprocess
Requires-Dist: PySimpleGUI
Requires-Dist: ujson
Requires-Dist: numpy
Requires-Dist: mpmath
Requires-Dist: twobitreader
Requires-Dist: intervaltree
Dynamic: author
Dynamic: author-email
Dynamic: classifier
Dynamic: description
Dynamic: description-content-type
Dynamic: home-page
Dynamic: keywords
Dynamic: license-file
Dynamic: project-url
Dynamic: requires-dist
Dynamic: requires-python
Dynamic: summary
